AccountManager/__init__.py
AccountManager/account_manager.py
BinanceAPI/__init__.py
BinanceAPI/backtest_engine.py
BinanceAPI/client.py
BinanceAPI/depthcache.py
BinanceAPI/enums.py
BinanceAPI/exceptions.py
BinanceAPI/helpers.py
BinanceAPI/websockets.py
Database/Database.py
Database/__init__.py
Keys/__init__.py
Keys/keys.py
OrderManager/__init__.py
OrderManager/order_manager.py
Scrappers/Scrapper_BQX:ETH.py
Scrappers/Scrapper_ETH:BTC.py
Scrappers/Scrapper_SALT:ETH.py
Scrappers/__init__.py
Symbols/__init__.py
Symbols/symbols.py
Block_Fund_Trading-1.0.dist-info/.DS_Store
Block_Fund_Trading-1.0.dist-info/LICENSE.txt
Block_Fund_Trading-1.0.dist-info/METADATA
Block_Fund_Trading-1.0.dist-info/README.md
Block_Fund_Trading-1.0.dist-info/WHEEL
Block_Fund_Trading-1.0.dist-info/top_level.txt
Block_Fund_Trading-1.0.dist-info/RECORD
