Metadata-Version: 2.1
Name: Block-Fund-Trading
Version: 1.0
Summary: ICO-python-trading
Home-page: UNKNOWN
Author: Maarten Elgar
Author-email: maartenelgar12@gmail.com
License: UNKNOWN
Platform: UNKNOWN
Classifier: Intended Audience :: Developers
Classifier: License :: OSI Approved :: MIT License
Classifier: Operating System :: OS Independent
Classifier: Programming Language :: Python :: 2
Classifier: Programming Language :: Python :: 2.7
Classifier: Programming Language :: Python :: 3
Classifier: Programming Language :: Python :: 3.3
Classifier: Programming Language :: Python :: 3.4
Classifier: Programming Language :: Python :: 3.5
Classifier: Programming Language :: Python :: 3.6
Classifier: Programming Language :: Python
Classifier: Topic :: Software Development :: Libraries :: Python Modules
Requires-Dist: requests
Requires-Dist: six
Requires-Dist: Twisted
Requires-Dist: pyOpenSSL
Requires-Dist: autobahn
Requires-Dist: service-identity
Requires-Dist: dateparser
Requires-Dist: urllib3
Requires-Dist: chardet
Requires-Dist: certifi
Requires-Dist: cryptography
Requires-Dist: pandas
Requires-Dist: numpy
Requires-Dist: os
